searchyt/__init__.py
searchyt/__main__.py
searchyt/searchyt.py
tests/__init__.py
tests/test_searchyt.py
searchyt-0.1.1.dist-info/LICENSE
searchyt-0.1.1.dist-info/METADATA
searchyt-0.1.1.dist-info/WHEEL
searchyt-0.1.1.dist-info/top_level.txt
searchyt-0.1.1.dist-info/zip-safe
searchyt-0.1.1.dist-info/RECORD
