Metadata-Version: 2.1
Name: searchyt
Version: 0.1.1
Summary: Lightweight Python 3 library for searching youtube videos without API key
Home-page: https://github.com/LaBlazer/searchyt
Author: La_Blazer
Author-email: blazer@lblzr.com
License: Apache License
Keywords: yt,youtube,search,scrape,videos,api,key
Platform: UNKNOWN
Classifier: Programming Language :: Python :: 3.6
Classifier: License :: OSI Approved :: Apache Software License
Classifier: Operating System :: OS Independent
Classifier: Topic :: Internet :: WWW/HTTP :: Indexing/Search
Classifier: Topic :: Multimedia :: Video
Classifier: Topic :: Utilities
Classifier: Development Status :: 4 - Beta
Classifier: Intended Audience :: Developers
Requires-Python: >=3.6
Requires-Dist: requests
